Workbook

Sheet Salary Silp
A1: CAPITAL BRIDGE PRIVATE LIMITED | E1: PAYSLIP
A2: No: 46/1, Thannekubura, Kandy
A3: Email: info@capitalbridge.lk Tel: 081 763 2009
A5: EMPLOYEE INFORMATION | C5: PAY DATE | D5: PAY TYPE | E5: Salary Month
A6: W M H M Weerasinghe | C6: =DATE(YEAR(E6), MONTH(E6), 25) -> 46259 | D6: Monthly | E6: 46235
A7: =IFERROR(INDEX('Employee Master'!$J:$J,MATCH($A$6,'Employee Master'!$A:$A,0)),"") -> 47/7/A | C7: PAYROLL # | D7: NI NUMBER
A8: =IFERROR(INDEX('Employee Master'!$K:$K,MATCH($A$6,'Employee Master'!$A:$A,0)),"") -> Richard Pamunuwa MW | C8: Position: | D8: =IFERROR(INDEX('Employee Master'!$C:$C,MATCH($A$6,'Employee Master'!$A:$A,0)),"") -> Assistant Accountant
A9: =IFERROR(INDEX('Employee Master'!$L:$L, MATCH($A$6, 'Employee Master'!$A:$A, 0)) & ".", "") -> Matale. | C9: Department | D9: =IFERROR(INDEX('Employee Master'!$D:$D,MATCH($A$6,'Employee Master'!$A:$A,0)),"") -> Finance & Accounts
A10: =IFERROR(INDEX('Employee Master'!$N:$N,MATCH($A$6,'Employee Master'!$A:$A,0)),"") -> 076-7597550
C11: Payment Method: | D11: Online
A13: EARNINGS | E13: CURRENT
A14: Basic Salary | E14: =IFERROR(SUMIFS('Salary Data'!$E:$E,'Salary Data'!$A:$A,$E$6,'Salary Data'!$B:$B,$A$6),0) -> 51500
A15: Budgeted Allowances | E15: =IFERROR(SUMIFS('Salary Data'!$F:$F,'Salary Data'!$A:$A,$E$6,'Salary Data'!$B:$B,$A$6),0) -> 3500
A16: Performance Allowances | E16: =IFERROR(SUMIFS('Salary Data'!$G:$G,'Salary Data'!$A:$A,$E$6,'Salary Data'!$B:$B,$A$6),0) -> 21000
A17: Field Allowances | E17: =IFERROR(SUMIFS('Salary Data'!$H:$H,'Salary Data'!$A:$A,$E$6,'Salary Data'!$B:$B,$A$6),0) -> 0
A18: Travelling Allowances | E18: =IFERROR(SUMIFS('Salary Data'!$I:$I,'Salary Data'!$A:$A,$E$6,'Salary Data'!$B:$B,$A$6),0) -> 10000
A19: Bike Maintained Allowance | E19: =IFERROR(SUMIFS('Salary Data'!$J:$J,'Salary Data'!$A:$A,$E$6,'Salary Data'!$B:$B,$A$6),0) -> 0
A20: Phone Allowance | E20: =IFERROR(SUMIFS('Salary Data'!$K:$K,'Salary Data'!$A:$A,$E$6,'Salary Data'!$B:$B,$A$6),0) -> 1000
A21: Incentives | E21: =IFERROR(SUMIFS('Salary Data'!$L:$L,'Salary Data'!$A:$A,$E$6,'Salary Data'!$B:$B,$A$6),0) -> 3000
C22: GROSS PAY | E22: =SUM(E14:E21) -> 90000
A24: DEDUCTIONS | E24: CURRENT
A25: EPF 8% | E25: =IFERROR(SUMIFS('Salary Data'!$N:$N,'Salary Data'!$A:$A,$E$6,'Salary Data'!$B:$B,$A$6),0) -> 4400
A26: Salary Advance | E26: =IFERROR(SUMIFS('Salary Data'!$O:$O,'Salary Data'!$A:$A,$E$6,'Salary Data'!$B:$B,$A$6),0) -> 0
A27: Travelling Advance | E27: =IFERROR(SUMIFS('Salary Data'!$P:$P,'Salary Data'!$A:$A,$E$6,'Salary Data'!$B:$B,$A$6),0) -> 0
A28: Staff Loan | D28: =IFERROR(INDEX('Salary Data'!$Z:$Z,MATCH($E$6&$A$6,'Salary Data'!$AA:$AA,0)),"") -> 6/10 | E28: =IFERROR(SUMIFS('Salary Data'!$Q:$Q,'Salary Data'!$A:$A,$E$6,'Salary Data'!$B:$B,$A$6),0) -> 10000
A29: Staff Loan Interest | E29: =IFERROR(SUMIFS('Salary Data'!$R:$R,'Salary Data'!$A:$A,$E$6,'Salary Data'!$B:$B,$A$6),0) -> 1500
A30: Other Deduction | E30: =IFERROR(SUMIFS('Salary Data'!$S:$S,'Salary Data'!$A:$A,$E$6,'Salary Data'!$B:$B,$A$6),0) -> 0
A31: Incentives Paid | E31: =IFERROR(SUMIFS('Salary Data'!$T:$T,'Salary Data'!$A:$A,$E$6,'Salary Data'!$B:$B,$A$6),0) -> 3000
A32: Paye Tax | E32: =IFERROR(SUMIFS('Salary Data'!$U:$U,'Salary Data'!$A:$A,$E$6,'Salary Data'!$B:$B,$A$6),0) -> 0
C33: TOTAL DEDUCTIONS | E33: =SUM(E25:E32) -> 18900
C35: NET PAY | E35: =E22-E33 -> 71100
C37: Employer Contributions | D37: EPF 12% | E37: =IFERROR(SUMIFS('Salary Data'!$X:$X,'Salary Data'!$A:$A,$E$6,'Salary Data'!$B:$B,$A$6),0) -> 6600
D38: ETF 3% | E38: =IFERROR(SUMIFS('Salary Data'!$Y:$Y,'Salary Data'!$A:$A,$E$6,'Salary Data'!$B:$B,$A$6),0) -> 1650
A43: ___________________________ | D43: ___________________________
A44: Prepared By | D44: Authorized Signature / Director
A46: If you have any questions about this payslip, please contact:
A47: [Capital bridge (Pvt) Ltd, Email: info@capitalbridge.lk Tel: 081 763 2009]

Sheet Employee Master
A1: Employee Name | B1: EPF No | C1: Designation | D1: Department | E1: Employment From | F1: Employment To | G1: NIC | H1: Age | I1: Address | J1: Address 01 | K1: Address 02 | L1: Address 03 | M1: Email | N1: Phone Number | O1: Active
A2: R A A S Ranasinghe | B2: 5 | C2: Director | D2: Executive Management | E2: 44197 | F2: =EDATE(DATE(IF(LEN(G2)=10, 1900+VALUE(MID(G2,1,2)), VALUE(MID(G2,1,4))), 1, VALUE(IF(LEN(G2)=10, MID(G2,3,3), MID(G2,5,3))) - IF(VALUE(IF(LEN(G2)=10, MID(G2,3,3), MID(G2,5,3)))>500, 500, 0)), 60*12) -> 50174 | G2: 771340318V | H2: =DATEDIF(DATE(IF(LEN(G2)=10, 1900+VALUE(MID(G2,1,2)), VALUE(MID(G2,1,4))), 1, VALUE(IF(LEN(G2)=10, MID(G2,3,3), MID(G2,5,3))) - IF(VALUE(IF(LEN(G2)=10, MID(G2,3,3), MID(G2,5,3)))>500, 500, 0)), TODAY(), "Y") -> 49 | I2: 3/1,Mawath 02, Aruppola, Kandy | J2: 32 | K2: Pikakanda Rd | L2: Kandy | N2: 077-2984772 | O2: Yes
A3: P G U N Wimalasooriya | B3: 10 | C3: Account Assistant | D3: Finance & Accounts | E3: 44927 | F3: =EDATE(DATE(IF(LEN(G3)=10, 1900+VALUE(MID(G3,1,2)), VALUE(MID(G3,1,4))), 1, VALUE(IF(LEN(G3)=10, MID(G3,3,3), MID(G3,5,3))) - IF(VALUE(IF(LEN(G3)=10, MID(G3,3,3), MID(G3,5,3)))>500, 500, 0)), 60*12) -> 58138 | G3: 995632985V | H3: =DATEDIF(DATE(IF(LEN(G3)=10, 1900+VALUE(MID(G3,1,2)), VALUE(MID(G3,1,4))), 1, VALUE(IF(LEN(G3)=10, MID(G3,3,3), MID(G3,5,3))) - IF(VALUE(IF(LEN(G3)=10, MID(G3,3,3), MID(G3,5,3)))>500, 500, 0)), TODAY(), "Y") -> 27 | I3: 218/C/1,Pahala Kondadeniya,Katugastota | J3: 218/C/1 | K3: Pahala Kondadeniya | L3: Katugastota | N3: 076-6447690 | O3: Yes
A4: N M A G M Peiris | B4: 16 | C4: Assistant Branch Maneger | D4: Loan Operations & Field | E4: 45524 | F4: =EDATE(DATE(IF(LEN(G4)=10, 1900+VALUE(MID(G4,1,2)), VALUE(MID(G4,1,4))), 1, VALUE(IF(LEN(G4)=10, MID(G4,3,3), MID(G4,5,3))) - IF(VALUE(IF(LEN(G4)=10, MID(G4,3,3), MID(G4,5,3)))>500, 500, 0)), 60*12) -> 55305 | G4: 911520591V | H4: =DATEDIF(DATE(IF(LEN(G4)=10, 1900+VALUE(MID(G4,1,2)), VALUE(MID(G4,1,4))), 1, VALUE(IF(LEN(G4)=10, MID(G4,3,3), MID(G4,5,3))) - IF(VALUE(IF(LEN(G4)=10, MID(G4,3,3), MID(G4,5,3)))>500, 500, 0)), TODAY(), "Y") -> 35 | I4: 104/2,Walgama,Handessa | J4: 104/2 | K4: Walgama | L4: Handessa | N4: 076-8090400 | O4: Yes
A5: K R T Hemantha | B5: 17 | C5: Field Executive | D5: Loan Operations & Field | E5: 45607 | F5: =EDATE(DATE(IF(LEN(G5)=10, 1900+VALUE(MID(G5,1,2)), VALUE(MID(G5,1,4))), 1, VALUE(IF(LEN(G5)=10, MID(G5,3,3), MID(G5,5,3))) - IF(VALUE(IF(LEN(G5)=10, MID(G5,3,3), MID(G5,5,3)))>500, 500, 0)), 60*12) -> 56635 | G5: 950211385V | H5: =DATEDIF(DATE(IF(LEN(G5)=10, 1900+VALUE(MID(G5,1,2)), VALUE(MID(G5,1,4))), 1, VALUE(IF(LEN(G5)=10, MID(G5,3,3), MID(G5,5,3))) - IF(VALUE(IF(LEN(G5)=10, MID(G5,3,3), MID(G5,5,3)))>500, 500, 0)), TODAY(), "Y") -> 31 | I5: 45/17,Nuwarathanna Rd,Waththegama | J5: 45/17 | K5: Nuwarathanna Rd | L5: Waththegama | N5: 074-3910206 | O5: Yes
A6: W M H M Weerasinghe | B6: 18 | C6: Assistant Accountant | D6: Finance & Accounts | E6: 45628 | F6: =EDATE(DATE(IF(LEN(G6)=10, 1900+VALUE(MID(G6,1,2)), VALUE(MID(G6,1,4))), 1, VALUE(IF(LEN(G6)=10, MID(G6,3,3), MID(G6,5,3))) - IF(VALUE(IF(LEN(G6)=10, MID(G6,3,3), MID(G6,5,3)))>500, 500, 0)), 60*12) -> 58326 | G6: 992512156V | H6: =DATEDIF(DATE(IF(LEN(G6)=10, 1900+VALUE(MID(G6,1,2)), VALUE(MID(G6,1,4))), 1, VALUE(IF(LEN(G6)=10, MID(G6,3,3), MID(G6,5,3))) - IF(VALUE(IF(LEN(G6)=10, MID(G6,3,3), MID(G6,5,3)))>500, 500, 0)), TODAY(), "Y") -> 27 | I6: 47/7/A,Richard Pamunuwa MW,Matale | J6: 47/7/A | K6: Richard Pamunuwa MW | L6: Matale | N6: 076-7597550 | O6: Yes
A7: R W D S Wijerathna | B7: 19 | C7: Field Executive | D7: Loan Operations & Field | E7: 45642 | F7: =EDATE(DATE(IF(LEN(G7)=10, 1900+VALUE(MID(G7,1,2)), VALUE(MID(G7,1,4))), 1, VALUE(IF(LEN(G7)=10, MID(G7,3,3), MID(G7,5,3))) - IF(VALUE(IF(LEN(G7)=10, MID(G7,3,3), MID(G7,5,3)))>500, 500, 0)), 60*12) -> 53780 | G7: 198708803218 | H7: =DATEDIF(DATE(IF(LEN(G7)=10, 1900+VALUE(MID(G7,1,2)), VALUE(MID(G7,1,4))), 1, VALUE(IF(LEN(G7)=10, MID(G7,3,3), MID(G7,5,3))) - IF(VALUE(IF(LEN(G7)=10, MID(G7,3,3), MID(G7,5,3)))>500, 500, 0)), TODAY(), "Y") -> 39 | I7: 19/1,Thannekubura,Kandy | J7: 19/1 | K7: Thannekubura | L7: Kandy | N7: 074-3365562 | O7: Yes
A8: S Wathmi Sankalpana | B8: 21 | C8: Trainee Account Clark | D8: Back Office | E8: 45659 | F8: =EDATE(DATE(IF(LEN(G8)=10, 1900+VALUE(MID(G8,1,2)), VALUE(MID(G8,1,4))), 1, VALUE(IF(LEN(G8)=10, MID(G8,3,3), MID(G8,5,3))) - IF(VALUE(IF(LEN(G8)=10, MID(G8,3,3), MID(G8,5,3)))>500, 500, 0)), 60*12) -> 60015 | G8: 200461403626 | H8: =DATEDIF(DATE(IF(LEN(G8)=10, 1900+VALUE(MID(G8,1,2)), VALUE(MID(G8,1,4))), 1, VALUE(IF(LEN(G8)=10, MID(G8,3,3), MID(G8,5,3))) - IF(VALUE(IF(LEN(G8)=10, MID(G8,3,3), MID(G8,5,3)))>500, 500, 0)), TODAY(), "Y") -> 22 | I8: 54,Alhena,Katawala Lewla | J8: 54 | K8: Alhena | L8: Katawala, Lewla | N8: 077-2745896 | O8: Yes
A9: E M P P W O R K Jayawardana | B9: 22 | C9: Trainee Field Executive | D9: Loan Operations & Field | E9: 45779 | F9: =EDATE(DATE(IF(LEN(G9)=10, 1900+VALUE(MID(G9,1,2)), VALUE(MID(G9,1,4))), 1, VALUE(IF(LEN(G9)=10, MID(G9,3,3), MID(G9,5,3))) - IF(VALUE(IF(LEN(G9)=10, MID(G9,3,3), MID(G9,5,3)))>500, 500, 0)), 60*12) -> 59970 | G9: 200406911756 | H9: =DATEDIF(DATE(IF(LEN(G9)=10, 1900+VALUE(MID(G9,1,2)), VALUE(MID(G9,1,4))), 1, VALUE(IF(LEN(G9)=10, MID(G9,3,3), MID(G9,5,3))) - IF(VALUE(IF(LEN(G9)=10, MID(G9,3,3), MID(G9,5,3)))>500, 500, 0)), TODAY(), "Y") -> 22 | I9: 103,Watapana,Putuhapuwa | J9: 103 | K9: Watapana | L9: Putuhapuwa | N9: 071-1074470 | O9: Yes
A10: T M R L B Thennakoon | B10: 23 | C10: Trainee Field Executive | D10: Loan Operations & Field | E10: 45845 | F10: =EDATE(DATE(IF(LEN(G10)=10, 1900+VALUE(MID(G10,1,2)), VALUE(MID(G10,1,4))), 1, VALUE(IF(LEN(G10)=10, MID(G10,3,3), MID(G10,5,3))) - IF(VALUE(IF(LEN(G10)=10, MID(G10,3,3), MID(G10,5,3)))>500, 500, 0)), 60*12) -> 60221 | G10: 200432000572 | H10: =DATEDIF(DATE(IF(LEN(G10)=10, 1900+VALUE(MID(G10,1,2)), VALUE(MID(G10,1,4))), 1, VALUE(IF(LEN(G10)=10, MID(G10,3,3), MID(G10,5,3))) - IF(VALUE(IF(LEN(G10)=10, MID(G10,3,3), MID(G10,5,3)))>500, 500, 0)), TODAY(), "Y") -> 21 | I10: No. 133/2, Nugepathana, Watapana, Putuhapuwa | J10: 133/2 | K10: Nugepathana | L10: Watapana, Putuhapuwa | N10: 072-7647478 | O10: Yes
A11: W K Senaverathna | B11: 24 | C11: Field Executive | D11: Loan Operations & Field | E11: 45875 | F11: =EDATE(DATE(IF(LEN(G11)=10, 1900+VALUE(MID(G11,1,2)), VALUE(MID(G11,1,4))), 1, VALUE(IF(LEN(G11)=10, MID(G11,3,3), MID(G11,5,3))) - IF(VALUE(IF(LEN(G11)=10, MID(G11,3,3), MID(G11,5,3)))>500, 500, 0)), 60*12) -> 57620 | G11: 972753432V | H11: =DATEDIF(DATE(IF(LEN(G11)=10, 1900+VALUE(MID(G11,1,2)), VALUE(MID(G11,1,4))), 1, VALUE(IF(LEN(G11)=10, MID(G11,3,3), MID(G11,5,3))) - IF(VALUE(IF(LEN(G11)=10, MID(G11,3,3), MID(G11,5,3)))>500, 500, 0)), TODAY(), "Y") -> 29 | I11: 173/1,Palkubura,Madawala,Harispaththuwa | J11: 173/1 | K11: Palkubura | L11: Madawala, Harispaththuwa | N11: 077-8115364 | O11: Yes
A12: D R G S L Ranaweera | B12: 25 | C12: Field Executive | D12: Loan Operations & Field | E12: 45937 | F12: =EDATE(DATE(IF(LEN(G12)=10, 1900+VALUE(MID(G12,1,2)), VALUE(MID(G12,1,4))), 1, VALUE(IF(LEN(G12)=10, MID(G12,3,3), MID(G12,5,3))) - IF(VALUE(IF(LEN(G12)=10, MID(G12,3,3), MID(G12,5,3)))>500, 500, 0)), 60*12) -> 59698 | G12: 200316201041 | H12: =DATEDIF(DATE(IF(LEN(G12)=10, 1900+VALUE(MID(G12,1,2)), VALUE(MID(G12,1,4))), 1, VALUE(IF(LEN(G12)=10, MID(G12,3,3), MID(G12,5,3))) - IF(VALUE(IF(LEN(G12)=10, MID(G12,3,3), MID(G12,5,3)))>500, 500, 0)), TODAY(), "Y") -> 23 | I12: 29/4,Ullandupitiya,Werellagama,Kandy | J12: 29/4 | K12: Ullandupitiya | L12: Werellagama, Kandy | N12: 074-2618166 | O12: Yes
A13: W A A Heshani Bandara | B13: 26 | C13: Trainee Account Clark | D13: Back Office | E13: 45971 | F13: =EDATE(DATE(IF(LEN(G13)=10, 1900+VALUE(MID(G13,1,2)), VALUE(MID(G13,1,4))), 1, VALUE(IF(LEN(G13)=10, MID(G13,3,3), MID(G13,5,3))) - IF(VALUE(IF(LEN(G13)=10, MID(G13,3,3), MID(G13,5,3)))>500, 500, 0)), 60*12) -> 60487 | G13: 200572003817 | H13: =DATEDIF(DATE(IF(LEN(G13)=10, 1900+VALUE(MID(G13,1,2)), VALUE(MID(G13,1,4))), 1, VALUE(IF(LEN(G13)=10, MID(G13,3,3), MID(G13,5,3))) - IF(VALUE(IF(LEN(G13)=10, MID(G13,3,3), MID(G13,5,3)))>500, 500, 0)), TODAY(), "Y") -> 21 | I13: 42/A,Haragama,Gurudeniya | J13: 42/A | K13: Haragama | L13: Gurudeniya | N13: 071-7297769 | O13: Yes
A14: D M T S Disanayake | B14: 27 | C14: Trainee Field Executive | D14: Loan Operations & Field | E14: 45978 | F14: =EDATE(DATE(IF(LEN(G14)=10, 1900+VALUE(MID(G14,1,2)), VALUE(MID(G14,1,4))), 1, VALUE(IF(LEN(G14)=10, MID(G14,3,3), MID(G14,5,3))) - IF(VALUE(IF(LEN(G14)=10, MID(G14,3,3), MID(G14,5,3)))>500, 500, 0)), 60*12) -> 60603 | G14: 200533602082 | H14: =DATEDIF(DATE(IF(LEN(G14)=10, 1900+VALUE(MID(G14,1,2)), VALUE(MID(G14,1,4))), 1, VALUE(IF(LEN(G14)=10, MID(G14,3,3), MID(G14,5,3))) - IF(VALUE(IF(LEN(G14)=10, MID(G14,3,3), MID(G14,5,3)))>500, 500, 0)), TODAY(), "Y") -> 20 | I14: 165/1,Amunugama,Gunnapana | J14: 165/1 | K14: Amunugama | L14: Gunnapana | N14: 075-0872988 | O14: Yes
A15: P L D B Wijewardhna | B15: 28 | C15: Field Executive | D15: Back Office | E15: 46023 | F15: =EDATE(DATE(IF(LEN(G15)=10, 1900+VALUE(MID(G15,1,2)), VALUE(MID(G15,1,4))), 1, VALUE(IF(LEN(G15)=10, MID(G15,3,3), MID(G15,5,3))) - IF(VALUE(IF(LEN(G15)=10, MID(G15,3,3), MID(G15,5,3)))>500, 500, 0)), 60*12) -> 57148 | G15: 199616902059 | H15: =DATEDIF(DATE(IF(LEN(G15)=10, 1900+VALUE(MID(G15,1,2)), VALUE(MID(G15,1,4))), 1, VALUE(IF(LEN(G15)=10, MID(G15,3,3), MID(G15,5,3))) - IF(VALUE(IF(LEN(G15)=10, MID(G15,3,3), MID(G15,5,3)))>500, 500, 0)), TODAY(), "Y") -> 30 | I15: 166,Jayabima,Arabegama,Werellagama | J15: 166 | K15: Jayabima | L15: Arabegama, Werellagama | N15: 077-6508664 | O15: Yes
A16: N G L D Supunsiri | B16: 29 | C16: Trainee Field Executive | D16: Loan Operations & Field | E16: 46104 | F16: =EDATE(DATE(IF(LEN(G16)=10, 1900+VALUE(MID(G16,1,2)), VALUE(MID(G16,1,4))), 1, VALUE(IF(LEN(G16)=10, MID(G16,3,3), MID(G16,5,3))) - IF(VALUE(IF(LEN(G16)=10, MID(G16,3,3), MID(G16,5,3)))>500, 500, 0)), 60*12) -> 60377 | G16: 200511002229 | H16: =DATEDIF(DATE(IF(LEN(G16)=10, 1900+VALUE(MID(G16,1,2)), VALUE(MID(G16,1,4))), 1, VALUE(IF(LEN(G16)=10, MID(G16,3,3), MID(G16,5,3))) - IF(VALUE(IF(LEN(G16)=10, MID(G16,3,3), MID(G16,5,3)))>500, 500, 0)), TODAY(), "Y") -> 21 | I16: 04, Hathmunna, Pilawala | J16: 4 | K16: Hathmunna | L16: Pilawala | N16: 077-6672131 | O16: Yes

Sheet Salary Data
A1: Month | B1: Employee Name | C1: EPF No | D1: Designation | E1: Basic Salary | F1: Budgeted Allowance | G1: Performance Allowance | H1: Field Allowance | I1: Travelling Allowance | J1: Bike Maintenance | K1: Phone Allowance | L1: Incentives | M1: Gross Salary | N1: EPF 8% | O1: Salary Advance | P1: Travelling Advance | Q1: Staff Loan | R1: Staff Loan Interest | S1: Other Deduction | T1: Incentives Paid | U1: PAYE Tax | V1: Total Deduction | W1: Net Salary | X1: EPF 12% | Y1: ETF 3% | Z1: Loan Instalement | AA1: Loan Instalement
A2: 46113 | B2: R A A S Ranasinghe | C2: 5 | D2: Director | E2: 61500 | F2: 3500 | G2: 53000 | H2: 0 | I2: 29000 | J2: 30000 | K2: 1000 | L2: 0 | M2: =SUM(E2:L2) -> 178000 | N2: =(E2+F2)*8% -> 5200 | O2: 0 | P2: 0 | Q2: 9250 | R2: 3700 | S2: 0 | T2: 0 | U2: 1680 | V2: =SUM(N2:U2) -> 19830 | W2: =M2-V2 -> 158170 | X2: =(E2+F2)*12% -> 7800 | Y2: =(E2+F2)*3% -> 1950 | Z2: 20/1 | AA2: =A2&B2 -> 46113R A A S Ranasinghe
A3: 46113 | B3: P G U N Wimalasooriya | C3: 10 | D3: Account Assistant | E3: 26500 | F3: 3500 | G3: 5000 | H3: 0 | I3: 7000 | J3: 0 | K3: 1000 | L3: 2000 | M3: =SUM(E3:L3) -> 45000 | N3: =(E3+F3)*8% -> 2400 | O3: 0 | P3: 0 | Q3: 10000 | R3: 600 | S3: 0 | T3: 2000 | U3: 0 | V3: =SUM(N3:U3) -> 15000 | W3: =M3-V3 -> 30000 | X3: =(E3+F3)*12% -> 3600 | Y3: =(E3+F3)*3% -> 900 | Z3: 2/3 | AA3: =A3&B3 -> 46113P G U N Wimalasooriya
A4: 46113 | B4: N M A G M Peiris | C4: 16 | D4: Assistant Branch Maneger | E4: 41500 | F4: 3500 | G4: 17000 | H4: 8000 | I4: 24360 | J4: 0 | K4: 1000 | L4: 3050 | M4: =SUM(E4:L4) -> 98410 | N4: =(E4+F4)*8% -> 3600 | O4: 10000 | P4: 0 | Q4: 12500 | R4: 750 | S4: 0 | T4: 3050 | U4: 0 | V4: =SUM(N4:U4) -> 29900 | W4: =M4-V4 -> 68510 | X4: =(E4+F4)*12% -> 5400 | Y4: =(E4+F4)*3% -> 1350 | Z4: 7/8 | AA4: =A4&B4 -> 46113N M A G M Peiris
A5: 46113 | B5: K R T Hemantha | C5: 17 | D5: Field Executive | E5: 31500 | F5: 3500 | G5: 7500 | H5: 5000 | I5: 24360 | J5: 10000 | K5: 1000 | L5: 3915 | M5: =SUM(E5:L5) -> 86775 | N5: =(E5+F5)*8% -> 2800 | O5: 12000 | P5: 0 | Q5: 10000 | R5: 1500 | S5: 0 | T5: 3915 | U5: 0 | V5: =SUM(N5:U5) -> 30215 | W5: =M5-V5 -> 56560 | X5: =(E5+F5)*12% -> 4200 | Y5: =(E5+F5)*3% -> 1050 | Z5: 3/7 | AA5: =A5&B5 -> 46113K R T Hemantha
A6: 46113 | B6: W M H M Weerasinghe | C6: 18 | D6: Assistant Accountant | E6: 51500 | F6: 3500 | G6: 21000 | H6: 0 | I6: 10000 | J6: 0 | K6: 1000 | L6: 2000 | M6: =SUM(E6:L6) -> 89000 | N6: =(E6+F6)*8% -> 4400 | O6: 0 | P6: 0 | Q6: 10000 | R6: 2700 | S6: 0 | T6: 2000 | U6: 0 | V6: =SUM(N6:U6) -> 19100 | W6: =M6-V6 -> 69900 | X6: =(E6+F6)*12% -> 6600 | Y6: =(E6+F6)*3% -> 1650 | Z6: 2/10 | AA6: =A6&B6 -> 46113W M H M Weerasinghe
A7: 46113 | B7: R W D S Wijerathna | C7: 19 | D7: Field Executive | E7: 36500 | F7: 3500 | G7: 7500 | H7: 5000 | I7: 24360 | J7: 10000 | K7: 1000 | L7: 11500 | M7: =SUM(E7:L7) -> 99360 | N7: =(E7+F7)*8% -> 3200 | O7: 0 | P7: 0 | Q7: 8333.33 | R7: 1500 | S7: 0 | T7: 11500 | U7: 0 | V7: =SUM(N7:U7) -> 24533.33 | W7: =M7-V7 -> 74826.67 | X7: =(E7+F7)*12% -> 4800 | Y7: =(E7+F7)*3% -> 1200 | Z7: 7/12 | AA7: =A7&B7 -> 46113R W D S Wijerathna
A8: 46113 | B8: S Wathmi Sankalpana | C8: 21 | D8: Trainee Account Clark | E8: 26500 | F8: 3500 | G8: 0 | H8: 0 | I8: 5000 | J8: 0 | K8: 1000 | L8: 2000 | M8: =SUM(E8:L8) -> 38000 | N8: =(E8+F8)*8% -> 2400 | O8: 0 | P8: 0 | Q8: 6000 | R8: 900 | S8: 0 | T8: 2000 | U8: 0 | V8: =SUM(N8:U8) -> 11300 | W8: =M8-V8 -> 26700 | X8: =(E8+F8)*12% -> 3600 | Y8: =(E8+F8)*3% -> 900 | Z8: 1/5 | AA8: =A8&B8 -> 46113S Wathmi Sankalpana
A9: 46113 | B9: E M P P W O R K Jayawardana | C9: 22 | D9: Trainee Field Executive | E9: 26500 | F9: 3500 | G9: 5000 | H9: 2760 | I9: 20880 | J9: 10000 | K9: 1000 | L9: 10175 | M9: =SUM(E9:L9) -> 79815 | N9: =(E9+F9)*8% -> 2400 | O9: 0 | P9: 0 | Q9: 5000 | R9: 2400 | S9: 0 | T9: 10175 | U9: 0 | V9: =SUM(N9:U9) -> 19975 | W9: =M9-V9 -> 59840 | X9: =(E9+F9)*12% -> 3600 | Y9: =(E9+F9)*3% -> 900 | Z9: 1/16 | AA9: =A9&B9 -> 46113E M P P W O R K Jayawardana
A10: 46113 | B10: T M R L B Thennakoon | C10: 23 | D10: Trainee Field Executive | E10: 26500 | F10: 3500 | G10: 7000 | H10: 5000 | I10: 20880 | J10: 0 | K10: 1000 | L10: 6272.5 | M10: =SUM(E10:L10) -> 70152.5 | N10: =(E10+F10)*8% -> 2400 | O10: 0 | P10: 0 | Q10: 10000 | R10: 1200 | S10: 0 | T10: 6272.5 | U10: 0 | V10: =SUM(N10:U10) -> 19872.5 | W10: =M10-V10 -> 50280 | X10: =(E10+F10)*12% -> 3600 | Y10: =(E10+F10)*3% -> 900 | Z10: 2/5 | AA10: =A10&B10 -> 46113T M R L B Thennakoon
A11: 46113 | B11: W K Senaverathna | C11: 24 | D11: Field Executive | E11: 31500 | F11: 3500 | G11: 7500 | H11: 5000 | I11: 20880 | J11: 0 | K11: 1000 | L11: 14525 | M11: =SUM(E11:L11) -> 83905 | N11: =(E11+F11)*8% -> 2800 | O11: 0 | P11: 0 | Q11: 0 | R11: 0 | S11: 0 | T11: 14525 | U11: 0 | V11: =SUM(N11:U11) -> 17325 | W11: =M11-V11 -> 66580 | X11: =(E11+F11)*12% -> 4200 | Y11: =(E11+F11)*3% -> 1050 | AA11: =A11&B11 -> 46113W K Senaverathna
A12: 46113 | B12: D R G S L Ranaweera | C12: 25 | D12: Field Executive | E12: 36500 | F12: 3500 | G12: 5000 | H12: 5000 | I12: 22620 | J12: 10000 | K12: 1000 | L12: 10650 | M12: =SUM(E12:L12) -> 94270 | N12: =(E12+F12)*8% -> 3200 | O12: 15000 | P12: 0 | Q12: 0 | R12: 0 | S12: 0 | T12: 10650 | U12: 0 | V12: =SUM(N12:U12) -> 28850 | W12: =M12-V12 -> 65420 | X12: =(E12+F12)*12% -> 4800 | Y12: =(E12+F12)*3% -> 1200 | AA12: =A12&B12 -> 46113D R G S L Ranaweera
A13: 46113 | B13: W A A Heshani Bandara | C13: 26 | D13: Trainee Account Clark | E13: 26500 | F13: 3500 | G13: 0 | H13: 0 | I13: 0 | J13: 0 | K13: 1000 | L13: 2000 | M13: =SUM(E13:L13) -> 33000 | N13: =(E13+F13)*8% -> 2400 | O13: 0 | P13: 0 | Q13: 0 | R13: 0 | S13: 0 | T13: 2000 | U13: 0 | V13: =SUM(N13:U13) -> 4400 | W13: =M13-V13 -> 28600 | X13: =(E13+F13)*12% -> 3600 | Y13: =(E13+F13)*3% -> 900 | AA13: =A13&B13 -> 46113W A A Heshani Bandara
A14: 46113 | B14: D M T S Disanayake | C14: 27 | D14: Trainee Field Executive | E14: 26500 | F14: 3500 | G14: 2500 | H14: 2500 | I14: 17400 | J14: 10000 | K14: 1000 | L14: 9675 | M14: =SUM(E14:L14) -> 73075 | N14: =(E14+F14)*8% -> 2400 | O14: 0 | P14: 0 | Q14: 10000 | R14: 2400 | S14: 0 | T14: 9675 | U14: 0 | V14: =SUM(N14:U14) -> 24475 | W14: =M14-V14 -> 48600 | X14: =(E14+F14)*12% -> 3600 | Y14: =(E14+F14)*3% -> 900 | Z14: 3/10 | AA14: =A14&B14 -> 46113D M T S Disanayake
A15: 46113 | B15: P L D B Wijewardhna | C15: 28 | D15: Field Executive | E15: 36500 | F15: 3500 | G15: 5000 | H15: 5000 | I15: 22620 | J15: 10000 | K15: 1000 | L15: 9272.5 | M15: =SUM(E15:L15) -> 92892.5 | N15: =(E15+F15)*8% -> 3200 | O15: 0 | P15: 0 | Q15: 0 | R15: 0 | S15: 0 | T15: 9272.5 | U15: 0 | V15: =SUM(N15:U15) -> 12472.5 | W15: =M15-V15 -> 80420 | X15: =(E15+F15)*12% -> 4800 | Y15: =(E15+F15)*3% -> 1200 | AA15: =A15&B15 -> 46113P L D B Wijewardhna
A16: 46113 | B16: N G L D Supunsiri | D16: Trainee Field Executive | E16: 0 | F16: 0 | G16: 30000 | H16: 0 | I16: 0 | J16: 0 | K16: 0 | L16: 0 | M16: =SUM(E16:L16) -> 30000 | N16: =(E16+F16)*8% -> 0 | O16: 0 | P16: 0 | Q16: 0 | R16: 0 | S16: 0 | T16: 0 | U16: 0 | V16: =SUM(N16:U16) -> 0 | W16: =M16-V16 -> 30000 | X16: =(E16+F16)*12% -> 0 | Y16: =(E16+F16)*3% -> 0 | AA16: =A16&B16 -> 46113N G L D Supunsiri
A17: 46143 | B17: R A A S Ranasinghe | C17: 5 | D17: Director | E17: 61500 | F17: 3500 | G17: 53000 | H17: 0 | I17: 29000 | J17: 30000 | K17: 1000 | L17: 0 | M17: =SUM(E17:L17) -> 178000 | N17: =(E17+F17)*8% -> 5200 | O17: 70000 | P17: 0 | Q17: 9250 | R17: 3515 | S17: 0 | T17: 0 | U17: 1680 | V17: =SUM(N17:U17) -> 89645 | W17: =M17-V17 -> 88355 | X17: =(E17+F17)*12% -> 7800 | Y17: =(E17+F17)*3% -> 1950 | Z17: 2/20 | AA17: =A17&B17 -> 46143R A A S Ranasinghe
A18: 46143 | B18: P G U N Wimalasooriya | C18: 10 | D18: Account Assistant | E18: 26500 | F18: 3500 | G18: 5000 | H18: 0 | I18: 7000 | J18: 0 | K18: 1000 | L18: 1500 | M18: =SUM(E18:L18) -> 44500 | N18: =(E18+F18)*8% -> 2400 | O18: 10000 | P18: 0 | Q18: 10000 | R18: 300 | S18: 0 | T18: 1500 | U18: 0 | V18: =SUM(N18:U18) -> 24200 | W18: =M18-V18 -> 20300 | X18: =(E18+F18)*12% -> 3600 | Y18: =(E18+F18)*3% -> 900 | Z18: 3/3 | AA18: =A18&B18 -> 46143P G U N Wimalasooriya
A19: 46143 | B19: N M A G M Peiris | C19: 16 | D19: Assistant Branch Maneger | E19: 41500 | F19: 3500 | G19: 17000 | H19: 8000 | I19: 24780 | J19: 0 | K19: 1000 | L19: 1380 | M19: =SUM(E19:L19) -> 97160 | N19: =(E19+F19)*8% -> 3600 | O19: 15000 | P19: 0 | Q19: 12500 | R19: 375 | S19: 0 | T19: 1380 | U19: 0 | V19: =SUM(N19:U19) -> 32855 | W19: =M19-V19 -> 64305 | X19: =(E19+F19)*12% -> 5400 | Y19: =(E19+F19)*3% -> 1350 | Z19: 8/8 | AA19: =A19&B19 -> 46143N M A G M Peiris
A20: 46143 | B20: K R T Hemantha | C20: 17 | D20: Field Executive | E20: 31500 | F20: 3500 | G20: 7500 | H20: 5000 | I20: 24780 | J20: 10000 | K20: 1000 | L20: 3620 | M20: =SUM(E20:L20) -> 86900 | N20: =(E20+F20)*8% -> 2800 | O20: 17000 | P20: 0 | Q20: 10000 | R20: 1200 | S20: 0 | T20: 3620 | U20: 0 | V20: =SUM(N20:U20) -> 34620 | W20: =M20-V20 -> 52280 | X20: =(E20+F20)*12% -> 4200 | Y20: =(E20+F20)*3% -> 1050 | Z20: 4/7 | AA20: =A20&B20 -> 46143K R T Hemantha
A21: 46143 | B21: W M H M Weerasinghe | C21: 18 | D21: Assistant Accountant | E21: 51500 | F21: 3500 | G21: 21000 | H21: 0 | I21: 10000 | J21: 0 | K21: 1000 | L21: 1500 | M21: =SUM(E21:L21) -> 88500 | N21: =(E21+F21)*8% -> 4400 | O21: 0 | P21: 0 | Q21: 10000 | R21: 2400 | S21: 0 | T21: 1500 | U21: 0 | V21: =SUM(N21:U21) -> 18300 | W21: =M21-V21 -> 70200 | X21: =(E21+F21)*12% -> 6600 | Y21: =(E21+F21)*3% -> 1650 | Z21: 3/10 | AA21: =A21&B21 -> 46143W M H M Weerasinghe
A22: 46143 | B22: R W D S Wijerathna | C22: 19 | D22: Field Executive | E22: 36500 | F22: 3500 | G22: 7500 | H22: 5000 | I22: 24780 | J22: 10000 | K22: 1000 | L22: 10000 | M22: =SUM(E22:L22) -> 98280 | N22: =(E22+F22)*8% -> 3200 | O22: 0 | P22: 0 | Q22: 8333.33 | R22: 1250 | S22: 0 | T22: 10000 | U22: 0 | V22: =SUM(N22:U22) -> 22783.33 | W22: =M22-V22 -> 75496.67 | X22: =(E22+F22)*12% -> 4800 | Y22: =(E22+F22)*3% -> 1200 | Z22: 8/12 | AA22: =A22&B22 -> 46143R W D S Wijerathna
A23: 46143 | B23: S Wathmi Sankalpana | C23: 21 | D23: Trainee Account Clark | E23: 26500 | F23: 3500 | G23: 0 | H23: 0 | I23: 5000 | J23: 0 | K23: 1000 | L23: 1500 | M23: =SUM(E23:L23) -> 37500 | N23: =(E23+F23)*8% -> 2400 | O23: 2000 | P23: 0 | Q23: 6000 | R23: 720 | S23: 0 | T23: 1500 | U23: 0 | V23: =SUM(N23:U23) -> 12620 | W23: =M23-V23 -> 24880 | X23: =(E23+F23)*12% -> 3600 | Y23: =(E23+F23)*3% -> 900 | Z23: 2/5 | AA23: =A23&B23 -> 46143S Wathmi Sankalpana
A24: 46143 | B24: E M P P W O R K Jayawardana | C24: 22 | D24: Trainee Field Executive | E24: 26500 | F24: 3500 | G24: 5000 | H24: 2760 | I24: 21240 | J24: 10000 | K24: 1000 | L24: 8000 | M24: =SUM(E24:L24) -> 78000 | N24: =(E24+F24)*8% -> 2400 | O24: 6000 | P24: 0 | Q24: 5000 | R24: 2250 | S24: 0 | T24: 8000 | U24: 0 | V24: =SUM(N24:U24) -> 23650 | W24: =M24-V24 -> 54350 | X24: =(E24+F24)*12% -> 3600 | Y24: =(E24+F24)*3% -> 900 | Z24: 2/16 | AA24: =A24&B24 -> 46143E M P P W O R K Jayawardana
A25: 46143 | B25: T M R L B Thennakoon | C25: 23 | D25: Trainee Field Executive | E25: 26500 | F25: 3500 | G25: 7000 | H25: 5000 | I25: 21240 | J25: 0 | K25: 1000 | L25: 1720 | M25: =SUM(E25:L25) -> 65960 | N25: =(E25+F25)*8% -> 2400 | O25: 6000 | P25: 0 | Q25: 10000 | R25: 900 | S25: 0 | T25: 1720 | U25: 0 | V25: =SUM(N25:U25) -> 21020 | W25: =M25-V25 -> 44940 | X25: =(E25+F25)*12% -> 3600 | Y25: =(E25+F25)*3% -> 900 | Z25: 3/5 | AA25: =A25&B25 -> 46143T M R L B Thennakoon
A26: 46143 | B26: W K Senaverathna | C26: 24 | D26: Field Executive | E26: 31500 | F26: 3500 | G26: 7500 | H26: 5000 | I26: 21240 | J26: 0 | K26: 1000 | L26: 11420 | M26: =SUM(E26:L26) -> 81160 | N26: =(E26+F26)*8% -> 2800 | O26: 0 | P26: 0 | Q26: 0 | R26: 0 | S26: 0 | T26: 11420 | U26: 0 | V26: =SUM(N26:U26) -> 14220 | W26: =M26-V26 -> 66940 | X26: =(E26+F26)*12% -> 4200 | Y26: =(E26+F26)*3% -> 1050 | AA26: =A26&B26 -> 46143W K Senaverathna
A27: 46143 | B27: D R G S L Ranaweera | C27: 25 | D27: Field Executive | E27: 36500 | F27: 3500 | G27: 5000 | H27: 5000 | I27: 23010 | J27: 10000 | K27: 1000 | L27: 7475 | M27: =SUM(E27:L27) -> 91485 | N27: =(E27+F27)*8% -> 3200 | O27: 15000 | P27: 0 | Q27: 10000 | R27: 1800 | S27: 0 | T27: 7475 | U27: 0 | V27: =SUM(N27:U27) -> 37475 | W27: =M27-V27 -> 54010 | X27: =(E27+F27)*12% -> 4800 | Y27: =(E27+F27)*3% -> 1200 | Z27: 1/6 | AA27: =A27&B27 -> 46143D R G S L Ranaweera
A28: 46143 | B28: W A A Heshani Bandara | C28: 26 | D28: Trainee Account Clark | E28: 26500 | F28: 3500 | G28: 0 | H28: 0 | I28: 0 | J28: 0 | K28: 1000 | L28: 1500 | M28: =SUM(E28:L28) -> 32500 | N28: =(E28+F28)*8% -> 2400 | O28: 0 | P28: 0 | Q28: 0 | R28: 0 | S28: 0 | T28: 1500 | U28: 0 | V28: =SUM(N28:U28) -> 3900 | W28: =M28-V28 -> 28600 | X28: =(E28+F28)*12% -> 3600 | Y28: =(E28+F28)*3% -> 900 | AA28: =A28&B28 -> 46143W A A Heshani Bandara
A29: 46143 | B29: D M T S Disanayake | C29: 27 | D29: Trainee Field Executive | E29: 26500 | F29: 3500 | G29: 2500 | H29: 2500 | I29: 17700 | J29: 10000 | K29: 1000 | L29: 4560 | M29: =SUM(E29:L29) -> 68260 | N29: =(E29+F29)*8% -> 2400 | O29: 5000 | P29: 0 | Q29: 10000 | R29: 2100 | S29: 0 | T29: 4560 | U29: 0 | V29: =SUM(N29:U29) -> 24060 | W29: =M29-V29 -> 44200 | X29: =(E29+F29)*12% -> 3600 | Y29: =(E29+F29)*3% -> 900 | Z29: 4/10 | AA29: =A29&B29 -> 46143D M T S Disanayake
A30: 46143 | B30: P L D B Wijewardhna | C30: 28 | D30: Field Executive | E30: 36500 | F30: 3500 | G30: 5000 | H30: 5000 | I30: 23010 | J30: 10000 | K30: 1000 | L30: 5000 | M30: =SUM(E30:L30) -> 89010 | N30: =(E30+F30)*8% -> 3200 | O30: 5000 | P30: 0 | Q30: 0 | R30: 0 | S30: 0 | T30: 5000 | U30: 0 | V30: =SUM(N30:U30) -> 13200 | W30: =M30-V30 -> 75810 | X30: =(E30+F30)*12% -> 4800 | Y30: =(E30+F30)*3% -> 1200 | AA30: =A30&B30 -> 46143P L D B Wijewardhna
A31: 46143 | B31: N G L D Supunsiri | D31: Trainee Field Executive | E31: 26500 | F31: 3500 | G31: 5000 | H31: 5000 | I31: 14160 | J31: 0 | K31: 1000 | L31: 0 | M31: =SUM(E31:L31) -> 55160 | N31: =(E31+F31)*8% -> 2400 | O31: 6000 | P31: 0 | Q31: 0 | R31: 0 | S31: 0 | T31: 0 | U31: 0 | V31: =SUM(N31:U31) -> 8400 | W31: =M31-V31 -> 46760 | X31: =(E31+F31)*12% -> 3600 | Y31: =(E31+F31)*3% -> 900 | AA31: =A31&B31 -> 46143N G L D Supunsiri
A32: 46174 | B32: R A A S Ranasinghe | C32: 5 | D32: Director | E32: 61500 | F32: 3500 | G32: 53000 | H32: 0 | I32: 29000 | J32: 30000 | K32: 1000 | L32: 0 | M32: =SUM(E32:L32) -> 178000 | N32: =(E32+F32)*8% -> 5200 | O32: 50000 | P32: 0 | Q32: 9250 | R32: 3330 | S32: 0 | T32: 0 | U32: 1680 | V32: =SUM(N32:U32) -> 69460 | W32: =M32-V32 -> 108540 | X32: =(E32+F32)*12% -> 7800 | Y32: =(E32+F32)*3% -> 1950 | Z32: 3/20 | AA32: =A32&B32 -> 46174R A A S Ranasinghe
A33: 46174 | B33: P G U N Wimalasooriya | C33: 10 | D33: Account Assistant | E33: 26500 | F33: 3500 | G33: 5000 | H33: 0 | I33: 7000 | J33: 0 | K33: 1000 | L33: 1000 | M33: =SUM(E33:L33) -> 44000 | N33: =(E33+F33)*8% -> 2400 | O33: 0 | P33: 0 | Q33: 10000 | R33: 900 | S33: 0 | T33: 1000 | U33: 0 | V33: =SUM(N33:U33) -> 14300 | W33: =M33-V33 -> 29700 | X33: =(E33+F33)*12% -> 3600 | Y33: =(E33+F33)*3% -> 900 | Z33: 1/3 | AA33: =A33&B33 -> 46174P G U N Wimalasooriya
A34: 46174 | B34: N M A G M Peiris | C34: 16 | D34: Assistant Branch Maneger | E34: 41500 | F34: 3500 | G34: 17000 | H34: 8000 | I34: 30380 | J34: 0 | K34: 1000 | L34: 2242.5 | M34: =SUM(E34:L34) -> 103622.5 | N34: =(E34+F34)*8% -> 3600 | O34: 5000 | P34: 0 | Q34: 5000 | R34: 1200 | S34: 0 | T34: 2242.5 | U34: 0 | V34: =SUM(N34:U34) -> 17042.5 | W34: =M34-V34 -> 86580 | X34: =(E34+F34)*12% -> 5400 | Y34: =(E34+F34)*3% -> 1350 | Z34: 1/8 | AA34: =A34&B34 -> 46174N M A G M Peiris
A35: 46174 | B35: K R T Hemantha | C35: 17 | D35: Field Executive | E35: 31500 | F35: 3500 | G35: 7500 | H35: 5000 | I35: 30380 | J35: 10000 | K35: 1000 | L35: 1050 | M35: =SUM(E35:L35) -> 89930 | N35: =(E35+F35)*8% -> 2800 | O35: 8000 | P35: 0 | Q35: 10000 | R35: 900 | S35: 0 | T35: 1050 | U35: 0 | V35: =SUM(N35:U35) -> 22750 | W35: =M35-V35 -> 67180 | X35: =(E35+F35)*12% -> 4200 | Y35: =(E35+F35)*3% -> 1050 | Z35: 5/7 | AA35: =A35&B35 -> 46174K R T Hemantha
A36: 46174 | B36: W M H M Weerasinghe | C36: 18 | D36: Assistant Accountant | E36: 51500 | F36: 3500 | G36: 21000 | H36: 0 | I36: 10000 | J36: 0 | K36: 1000 | L36: 1000 | M36: =SUM(E36:L36) -> 88000 | N36: =(E36+F36)*8% -> 4400 | O36: 0 | P36: 0 | Q36: 10000 | R36: 2100 | S36: 0 | T36: 1000 | U36: 0 | V36: =SUM(N36:U36) -> 17500 | W36: =M36-V36 -> 70500 | X36: =(E36+F36)*12% -> 6600 | Y36: =(E36+F36)*3% -> 1650 | Z36: 4/10 | AA36: =A36&B36 -> 46174W M H M Weerasinghe
A37: 46174 | B37: R W D S Wijerathna | C37: 19 | D37: Field Executive | E37: 36500 | F37: 3500 | G37: 7500 | H37: 5000 | I37: 30380 | J37: 10000 | K37: 1000 | L37: 8500 | M37: =SUM(E37:L37) -> 102380 | N37: =(E37+F37)*8% -> 3200 | O37: 0 | P37: 0 | Q37: 8333.33 | R37: 1000 | S37: 0 | T37: 8500 | U37: 0 | V37: =SUM(N37:U37) -> 21033.33 | W37: =M37-V37 -> 81346.67 | X37: =(E37+F37)*12% -> 4800 | Y37: =(E37+F37)*3% -> 1200 | Z37: 9/12 | AA37: =A37&B37 -> 46174R W D S Wijerathna
A38: 46174 | B38: S Wathmi Sankalpana | C38: 21 | D38: Trainee Account Clark | E38: 26500 | F38: 3500 | G38: 0 | H38: 0 | I38: 5000 | J38: 0 | K38: 1000 | L38: 1000 | M38: =SUM(E38:L38) -> 37000 | N38: =(E38+F38)*8% -> 2400 | O38: 10000 | P38: 0 | Q38: 6000 | R38: 540 | S38: 0 | T38: 1000 | U38: 0 | V38: =SUM(N38:U38) -> 19940 | W38: =M38-V38 -> 17060 | X38: =(E38+F38)*12% -> 3600 | Y38: =(E38+F38)*3% -> 900 | Z38: 3/5 | AA38: =A38&B38 -> 46174S Wathmi Sankalpana
A39: 46174 | B39: E M P P W O R K Jayawardana | C39: 22 | D39: Trainee Field Executive | E39: 26500 | F39: 3500 | G39: 5000 | H39: 2760 | I39: 26040 | J39: 10000 | K39: 1000 | L39: 4850 | M39: =SUM(E39:L39) -> 79650 | N39: =(E39+F39)*8% -> 2400 | O39: 0 | P39: 0 | Q39: 5000 | R39: 2100 | S39: 0 | T39: 4850 | U39: 0 | V39: =SUM(N39:U39) -> 14350 | W39: =M39-V39 -> 65300 | X39: =(E39+F39)*12% -> 3600 | Y39: =(E39+F39)*3% -> 900 | Z39: 3/16 | AA39: =A39&B39 -> 46174E M P P W O R K Jayawardana
A40: 46174 | B40: T M R L B Thennakoon | C40: 23 | D40: Trainee Field Executive | E40: 26500 | F40: 3500 | G40: 7000 | H40: 5000 | I40: 26040 | J40: 0 | K40: 1000 | L40: 3420 | M40: =SUM(E40:L40) -> 72460 | N40: =(E40+F40)*8% -> 2400 | O40: 6000 | P40: 0 | Q40: 10000 | R40: 600 | S40: 0 | T40: 3420 | U40: 0 | V40: =SUM(N40:U40) -> 22420 | W40: =M40-V40 -> 50040 | X40: =(E40+F40)*12% -> 3600 | Y40: =(E40+F40)*3% -> 900 | Z40: 4/5 | AA40: =A40&B40 -> 46174T M R L B Thennakoon
A41: 46174 | B41: W K Senaverathna | C41: 24 | D41: Field Executive | E41: 31500 | F41: 3500 | G41: 7500 | H41: 5000 | I41: 26040 | J41: 0 | K41: 1000 | L41: 6085 | M41: =SUM(E41:L41) -> 80625 | N41: =(E41+F41)*8% -> 2800 | O41: 10000 | P41: 0 | Q41: 0 | R41: 0 | S41: 0 | T41: 6085 | U41: 0 | V41: =SUM(N41:U41) -> 18885 | W41: =M41-V41 -> 61740 | X41: =(E41+F41)*12% -> 4200 | Y41: =(E41+F41)*3% -> 1050 | AA41: =A41&B41 -> 46174W K Senaverathna
A42: 46174 | B42: D R G S L Ranaweera | C42: 25 | D42: Field Executive | E42: 36500 | F42: 3500 | G42: 5000 | H42: 5000 | I42: 28210 | J42: 10000 | K42: 1000 | L42: 4600 | M42: =SUM(E42:L42) -> 93810 | N42: =(E42+F42)*8% -> 3200 | O42: 20000 | P42: 0 | Q42: 10000 | R42: 1500 | S42: 0 | T42: 4600 | U42: 0 | V42: =SUM(N42:U42) -> 39300 | W42: =M42-V42 -> 54510 | X42: =(E42+F42)*12% -> 4800 | Y42: =(E42+F42)*3% -> 1200 | Z42: 2/6 | AA42: =A42&B42 -> 46174D R G S L Ranaweera
A43: 46174 | B43: W A A Heshani Bandara | C43: 26 | D43: Trainee Account Clark | E43: 26500 | F43: 3500 | G43: 0 | H43: 0 | I43: 0 | J43: 0 | K43: 1000 | L43: 1000 | M43: =SUM(E43:L43) -> 32000 | N43: =(E43+F43)*8% -> 2400 | O43: 0 | P43: 0 | Q43: 0 | R43: 0 | S43: 0 | T43: 1000 | U43: 0 | V43: =SUM(N43:U43) -> 3400 | W43: =M43-V43 -> 28600 | X43: =(E43+F43)*12% -> 3600 | Y43: =(E43+F43)*3% -> 900 | AA43: =A43&B43 -> 46174W A A Heshani Bandara
A44: 46174 | B44: D M T S Disanayake | C44: 27 | D44: Trainee Field Executive | E44: 26500 | F44: 3500 | G44: 2500 | H44: 2500 | I44: 21700 | J44: 10000 | K44: 1000 | L44: 6835 | M44: =SUM(E44:L44) -> 74535 | N44: =(E44+F44)*8% -> 2400 | O44: 15000 | P44: 0 | Q44: 10000 | R44: 1800 | S44: 0 | T44: 6835 | U44: 0 | V44: =SUM(N44:U44) -> 36035 | W44: =M44-V44 -> 38500 | X44: =(E44+F44)*12% -> 3600 | Y44: =(E44+F44)*3% -> 900 | Z44: 5/10 | AA44: =A44&B44 -> 46174D M T S Disanayake
A45: 46174 | B45: P L D B Wijewardhna | C45: 28 | D45: Field Executive | E45: 36500 | F45: 3500 | G45: 5000 | H45: 5000 | I45: 28210 | J45: 10000 | K45: 1000 | L45: 3580 | M45: =SUM(E45:L45) -> 92790 | N45: =(E45+F45)*8% -> 3200 | O45: 10500 | P45: 0 | Q45: 0 | R45: 0 | S45: 0 | T45: 3580 | U45: 0 | V45: =SUM(N45:U45) -> 17280 | W45: =M45-V45 -> 75510 | X45: =(E45+F45)*12% -> 4800 | Y45: =(E45+F45)*3% -> 1200 | AA45: =A45&B45 -> 46174P L D B Wijewardhna
A46: 46174 | B46: N G L D Supunsiri | C46: 29 | D46: Trainee Field Executive | E46: 26500 | F46: 3500 | G46: 5000 | H46: 5000 | I46: 17360 | J46: 0 | K46: 1000 | L46: 0 | M46: =SUM(E46:L46) -> 58360 | N46: =(E46+F46)*8% -> 2400 | O46: 5000 | P46: 0 | Q46: 0 | R46: 0 | S46: 0 | T46: 0 | U46: 0 | V46: =SUM(N46:U46) -> 7400 | W46: =M46-V46 -> 50960 | X46: =(E46+F46)*12% -> 3600 | Y46: =(E46+F46)*3% -> 900 | AA46: =A46&B46 -> 46174N G L D Supunsiri
A47: 46204 | B47: R A A S Ranasinghe | C47: 5 | D47: Director | E47: 61500 | F47: 3500 | G47: 53000 | H47: 0 | I47: 29000 | J47: 30000 | K47: 1000 | L47: 0 | M47: =SUM(E47:L47) -> 178000 | N47: =(E47+F47)*8% -> 5200 | O47: 100000 | P47: 0 | Q47: 9250 | R47: 3145 | S47: 0 | T47: 0 | U47: 1680 | V47: =SUM(N47:U47) -> 119275 | W47: =M47-V47 -> 58725 | X47: =(E47+F47)*12% -> 7800 | Y47: =(E47+F47)*3% -> 1950 | Z47: 4/20 | AA47: =A47&B47 -> 46204R A A S Ranasinghe
A48: 46204 | B48: P G U N Wimalasooriya | C48: 10 | D48: Account Assistant | E48: 26500 | F48: 3500 | G48: 5000 | H48: 0 | I48: 7000 | J48: 0 | K48: 1000 | L48: 2000 | M48: =SUM(E48:L48) -> 45000 | N48: =(E48+F48)*8% -> 2400 | O48: 16000 | P48: 0 | Q48: 10000 | R48: 600 | S48: 0 | T48: 2000 | U48: 0 | V48: =SUM(N48:U48) -> 31000 | W48: =M48-V48 -> 14000 | X48: =(E48+F48)*12% -> 3600 | Y48: =(E48+F48)*3% -> 900 | Z48: 2/3 | AA48: =A48&B48 -> 46204P G U N Wimalasooriya
A49: 46204 | B49: N M A G M Peiris | C49: 16 | D49: Assistant Branch Maneger | E49: 41500 | F49: 3500 | G49: 17000 | H49: 8000 | I49: 28980 | J49: 0 | K49: 1000 | L49: 5085 | M49: =SUM(E49:L49) -> 105065 | N49: =(E49+F49)*8% -> 3600 | O49: 15000 | P49: 0 | Q49: 5000 | R49: 1050 | S49: 0 | T49: 5085 | U49: 0 | V49: =SUM(N49:U49) -> 29735 | W49: =M49-V49 -> 75330 | X49: =(E49+F49)*12% -> 5400 | Y49: =(E49+F49)*3% -> 1350 | Z49: 2/8 | AA49: =A49&B49 -> 46204N M A G M Peiris
A50: 46204 | B50: K R T Hemantha | C50: 17 | D50: Field Executive | E50: 31500 | F50: 3500 | G50: 7500 | H50: 5000 | I50: 28980 | J50: 10000 | K50: 1000 | L50: 3050 | M50: =SUM(E50:L50) -> 90530 | N50: =(E50+F50)*8% -> 2800 | O50: 12000 | P50: 0 | Q50: 10000 | R50: 600 | S50: 0 | T50: 3050 | U50: 0 | V50: =SUM(N50:U50) -> 28450 | W50: =M50-V50 -> 62080 | X50: =(E50+F50)*12% -> 4200 | Y50: =(E50+F50)*3% -> 1050 | Z50: 6/7 | AA50: =A50&B50 -> 46204K R T Hemantha
A51: 46204 | B51: W M H M Weerasinghe | C51: 18 | D51: Assistant Accountant | E51: 51500 | F51: 3500 | G51: 21000 | H51: 0 | I51: 10000 | J51: 0 | K51: 1000 | L51: 2000 | M51: =SUM(E51:L51) -> 89000 | N51: =(E51+F51)*8% -> 4400 | O51: 0 | P51: 0 | Q51: 10000 | R51: 1800 | S51: 0 | T51: 2000 | U51: 0 | V51: =SUM(N51:U51) -> 18200 | W51: =M51-V51 -> 70800 | X51: =(E51+F51)*12% -> 6600 | Y51: =(E51+F51)*3% -> 1650 | Z51: 5/10 | AA51: =A51&B51 -> 46204W M H M Weerasinghe
A52: 46204 | B52: R W D S Wijerathna | C52: 19 | D52: Field Executive | E52: 36500 | F52: 3500 | G52: 7500 | H52: 5000 | I52: 28980 | J52: 10000 | K52: 1000 | L52: 10000 | M52: =SUM(E52:L52) -> 102480 | N52: =(E52+F52)*8% -> 3200 | O52: 0 | P52: 0 | Q52: 8333.33 | R52: 750 | S52: 0 | T52: 10000 | U52: 0 | V52: =SUM(N52:U52) -> 22283.33 | W52: =M52-V52 -> 80196.67 | X52: =(E52+F52)*12% -> 4800 | Y52: =(E52+F52)*3% -> 1200 | Z52: 10/12 | AA52: =A52&B52 -> 46204R W D S Wijerathna
A53: 46204 | B53: S Wathmi Sankalpana | C53: 21 | D53: Trainee Account Clark | E53: 26500 | F53: 3500 | G53: 0 | H53: 0 | I53: 5000 | J53: 0 | K53: 1000 | L53: 2000 | M53: =SUM(E53:L53) -> 38000 | N53: =(E53+F53)*8% -> 2400 | O53: 10000 | P53: 0 | Q53: 6000 | R53: 360 | S53: 0 | T53: 2000 | U53: 0 | V53: =SUM(N53:U53) -> 20760 | W53: =M53-V53 -> 17240 | X53: =(E53+F53)*12% -> 3600 | Y53: =(E53+F53)*3% -> 900 | Z53: 4/5 | AA53: =A53&B53 -> 46204S Wathmi Sankalpana
A54: 46204 | B54: E M P P W O R K Jayawardana | C54: 22 | D54: Trainee Field Executive | E54: 26500 | F54: 3500 | G54: 5000 | H54: 2760 | I54: 26910 | J54: 10000 | K54: 1000 | L54: 8380 | M54: =SUM(E54:L54) -> 84050 | N54: =(E54+F54)*8% -> 2400 | O54: 5000 | P54: 0 | Q54: 5000 | R54: 1950 | S54: 0 | T54: 8380 | U54: 0 | V54: =SUM(N54:U54) -> 22730 | W54: =M54-V54 -> 61320 | X54: =(E54+F54)*12% -> 3600 | Y54: =(E54+F54)*3% -> 900 | Z54: 4/16 | AA54: =A54&B54 -> 46204E M P P W O R K Jayawardana
A55: 46204 | B55: T M R L B Thennakoon | C55: 23 | D55: Trainee Field Executive | E55: 26500 | F55: 3500 | G55: 7000 | H55: 5000 | I55: 26910 | J55: 0 | K55: 1000 | L55: 5250 | M55: =SUM(E55:L55) -> 75160 | N55: =(E55+F55)*8% -> 2400 | O55: 5000 | P55: 0 | Q55: 10000 | R55: 300 | S55: 0 | T55: 5250 | U55: 0 | V55: =SUM(N55:U55) -> 22950 | W55: =M55-V55 -> 52210 | X55: =(E55+F55)*12% -> 3600 | Y55: =(E55+F55)*3% -> 900 | Z55: 5/5 | AA55: =A55&B55 -> 46204T M R L B Thennakoon
A56: 46204 | B56: W K Senaverathna | C56: 24 | D56: Field Executive | E56: 31500 | F56: 3500 | G56: 7500 | H56: 5000 | I56: 26910 | J56: 0 | K56: 1000 | L56: 7640 | M56: =SUM(E56:L56) -> 83050 | N56: =(E56+F56)*8% -> 2800 | O56: 0 | P56: 0 | Q56: 0 | R56: 0 | S56: 0 | T56: 7640 | U56: 0 | V56: =SUM(N56:U56) -> 10440 | W56: =M56-V56 -> 72610 | X56: =(E56+F56)*12% -> 4200 | Y56: =(E56+F56)*3% -> 1050 | AA56: =A56&B56 -> 46204W K Senaverathna
A57: 46204 | B57: D R G S L Ranaweera | C57: 25 | D57: Field Executive | E57: 36500 | F57: 3500 | G57: 5000 | H57: 5000 | I57: 26910 | J57: 10000 | K57: 1000 | L57: 5150 | M57: =SUM(E57:L57) -> 93060 | N57: =(E57+F57)*8% -> 3200 | O57: 17000 | P57: 0 | Q57: 10000 | R57: 1200 | S57: 0 | T57: 5150 | U57: 0 | V57: =SUM(N57:U57) -> 36550 | W57: =M57-V57 -> 56510 | X57: =(E57+F57)*12% -> 4800 | Y57: =(E57+F57)*3% -> 1200 | Z57: 3/6 | AA57: =A57&B57 -> 46204D R G S L Ranaweera
A58: 46204 | B58: W A A Heshani Bandara | C58: 26 | D58: Trainee Account Clark | E58: 26500 | F58: 3500 | G58: 0 | H58: 0 | I58: 0 | J58: 0 | K58: 1000 | L58: 2000 | M58: =SUM(E58:L58) -> 33000 | N58: =(E58+F58)*8% -> 2400 | O58: 0 | P58: 0 | Q58: 0 | R58: 0 | S58: 0 | T58: 2000 | U58: 0 | V58: =SUM(N58:U58) -> 4400 | W58: =M58-V58 -> 28600 | X58: =(E58+F58)*12% -> 3600 | Y58: =(E58+F58)*3% -> 900 | AA58: =A58&B58 -> 46204W A A Heshani Bandara
A59: 46204 | B59: D M T S Disanayake | C59: 27 | D59: Trainee Field Executive | E59: 26500 | F59: 3500 | G59: 2500 | H59: 2500 | I59: 24840 | J59: 10000 | K59: 1000 | L59: 8700 | M59: =SUM(E59:L59) -> 79540 | N59: =(E59+F59)*8% -> 2400 | O59: 13000 | P59: 0 | Q59: 10000 | R59: 1500 | S59: 0 | T59: 8700 | U59: 0 | V59: =SUM(N59:U59) -> 35600 | W59: =M59-V59 -> 43940 | X59: =(E59+F59)*12% -> 3600 | Y59: =(E59+F59)*3% -> 900 | Z59: 6/10 | AA59: =A59&B59 -> 46204D M T S Disanayake
A60: 46204 | B60: P L D B Wijewardhna | C60: 28 | D60: Field Executive | E60: 36500 | F60: 3500 | G60: 10000 | H60: 5000 | I60: 26910 | J60: 10000 | K60: 1000 | L60: 4645 | M60: =SUM(E60:L60) -> 97555 | N60: =(E60+F60)*8% -> 3200 | O60: 9000 | P60: 0 | Q60: 0 | R60: 0 | S60: 0 | T60: 4645 | U60: 0 | V60: =SUM(N60:U60) -> 16845 | W60: =M60-V60 -> 80710 | X60: =(E60+F60)*12% -> 4800 | Y60: =(E60+F60)*3% -> 1200 | AA60: =A60&B60 -> 46204P L D B Wijewardhna
A61: 46204 | B61: N G L D Supunsiri | C61: 29 | D61: Trainee Field Executive | E61: 26500 | F61: 3500 | G61: 5000 | H61: 5000 | I61: 18630 | J61: 0 | K61: 1000 | L61: 0 | M61: =SUM(E61:L61) -> 59630 | N61: =(E61+F61)*8% -> 2400 | O61: 11800 | P61: 0 | Q61: 0 | R61: 0 | S61: 0 | T61: 0 | U61: 0 | V61: =SUM(N61:U61) -> 14200 | W61: =M61-V61 -> 45430 | X61: =(E61+F61)*12% -> 3600 | Y61: =(E61+F61)*3% -> 900 | AA61: =A61&B61 -> 46204N G L D Supunsiri
A62: 46235 | B62: R A A S Ranasinghe | C62: 5 | D62: Director | E62: 61500 | F62: 3500 | G62: 53000 | H62: 0 | I62: 29000 | J62: 30000 | K62: 1000 | L62: 0 | M62: =SUM(E62:L62) -> 178000 | N62: =(E62+F62)*8% -> 5200 | O62: 50000 | P62: 0 | Q62: 9250 | R62: 2960 | S62: 0 | T62: 0 | U62: 1680 | V62: =SUM(N62:U62) -> 69090 | W62: =M62-V62 -> 108910 | X62: =(E62+F62)*12% -> 7800 | Y62: =(E62+F62)*3% -> 1950 | Z62: 5/20 | AA62: =A62&B62 -> 46235R A A S Ranasinghe
A63: 46235 | B63: P G U N Wimalasooriya | C63: 10 | D63: Account Assistant | E63: 26500 | F63: 3500 | G63: 5000 | H63: 0 | I63: 7000 | J63: 0 | K63: 1000 | L63: 3000 | M63: =SUM(E63:L63) -> 46000 | N63: =(E63+F63)*8% -> 2400 | O63: 0 | P63: 0 | Q63: 10000 | R63: 300 | S63: 0 | T63: 3000 | U63: 0 | V63: =SUM(N63:U63) -> 15700 | W63: =M63-V63 -> 30300 | X63: =(E63+F63)*12% -> 3600 | Y63: =(E63+F63)*3% -> 900 | Z63: 3/3 | AA63: =A63&B63 -> 46235P G U N Wimalasooriya
A64: 46235 | B64: N M A G M Peiris | C64: 16 | D64: Assistant Branch Maneger | E64: 41500 | F64: 3500 | G64: 17000 | H64: 8000 | I64: 28980 | J64: 0 | K64: 1000 | L64: 3000 | M64: =SUM(E64:L64) -> 102980 | N64: =(E64+F64)*8% -> 3600 | O64: 18000 | P64: 0 | Q64: 5000 | R64: 900 | S64: 0 | T64: 3000 | U64: 0 | V64: =SUM(N64:U64) -> 30500 | W64: =M64-V64 -> 72480 | X64: =(E64+F64)*12% -> 5400 | Y64: =(E64+F64)*3% -> 1350 | Z64: 3/8 | AA64: =A64&B64 -> 46235N M A G M Peiris
A65: 46235 | B65: K R T Hemantha | C65: 17 | D65: Field Executive | E65: 31500 | F65: 3500 | G65: 7500 | H65: 5000 | I65: 28980 | J65: 10000 | K65: 1000 | L65: 5850 | M65: =SUM(E65:L65) -> 93330 | N65: =(E65+F65)*8% -> 2800 | O65: 11000 | P65: 0 | Q65: 20000 | R65: 1200 | S65: 0 | T65: 5850 | U65: 0 | V65: =SUM(N65:U65) -> 40850 | W65: =M65-V65 -> 52480 | X65: =(E65+F65)*12% -> 4200 | Y65: =(E65+F65)*3% -> 1050 | Z65: 1/2 | AA65: =A65&B65 -> 46235K R T Hemantha
A66: 46235 | B66: W M H M Weerasinghe | C66: 18 | D66: Assistant Accountant | E66: 51500 | F66: 3500 | G66: 21000 | H66: 0 | I66: 10000 | J66: 0 | K66: 1000 | L66: 3000 | M66: =SUM(E66:L66) -> 90000 | N66: =(E66+F66)*8% -> 4400 | O66: 0 | P66: 0 | Q66: 10000 | R66: 1500 | S66: 0 | T66: 3000 | U66: 0 | V66: =SUM(N66:U66) -> 18900 | W66: =M66-V66 -> 71100 | X66: =(E66+F66)*12% -> 6600 | Y66: =(E66+F66)*3% -> 1650 | Z66: 6/10 | AA66: =A66&B66 -> 46235W M H M Weerasinghe
A67: 46235 | B67: R W D S Wijerathna | C67: 19 | D67: Field Executive | E67: 36500 | F67: 3500 | G67: 7500 | H67: 5000 | I67: 28980 | J67: 10000 | K67: 1000 | L67: 8500 | M67: =SUM(E67:L67) -> 100980 | N67: =(E67+F67)*8% -> 3200 | O67: 0 | P67: 0 | Q67: 8333.33 | R67: 500 | S67: 0 | T67: 8500 | U67: 0 | V67: =SUM(N67:U67) -> 20533.33 | W67: =M67-V67 -> 80446.67 | X67: =(E67+F67)*12% -> 4800 | Y67: =(E67+F67)*3% -> 1200 | Z67: 11/12 | AA67: =A67&B67 -> 46235R W D S Wijerathna
A68: 46235 | B68: S Wathmi Sankalpana | C68: 21 | D68: Trainee Account Clark | E68: 26500 | F68: 3500 | G68: 0 | H68: 0 | I68: 5000 | J68: 0 | K68: 1000 | L68: 3000 | M68: =SUM(E68:L68) -> 39000 | N68: =(E68+F68)*8% -> 2400 | O68: 3500 | P68: 0 | Q68: 6000 | R68: 180 | S68: 0 | T68: 3000 | U68: 0 | V68: =SUM(N68:U68) -> 15080 | W68: =M68-V68 -> 23920 | X68: =(E68+F68)*12% -> 3600 | Y68: =(E68+F68)*3% -> 900 | Z68: 5/5 | AA68: =A68&B68 -> 46235S Wathmi Sankalpana
A69: 46235 | B69: E M P P W O R K Jayawardana | C69: 22 | D69: Trainee Field Executive | E69: 26500 | F69: 3500 | G69: 5000 | H69: 2760 | I69: 26910 | J69: 10000 | K69: 1000 | L69: 5260 | M69: =SUM(E69:L69) -> 80930 | N69: =(E69+F69)*8% -> 2400 | O69: 10000 | P69: 0 | Q69: 5000 | R69: 1800 | S69: 0 | T69: 5260 | U69: 0 | V69: =SUM(N69:U69) -> 24460 | W69: =M69-V69 -> 56470 | X69: =(E69+F69)*12% -> 3600 | Y69: =(E69+F69)*3% -> 900 | Z69: 5/16 | AA69: =A69&B69 -> 46235E M P P W O R K Jayawardana
A70: 46235 | B70: T M R L B Thennakoon | C70: 23 | D70: Trainee Field Executive | E70: 26500 | F70: 3500 | G70: 7000 | H70: 5000 | I70: 26910 | J70: 0 | K70: 1000 | L70: 4480 | M70: =SUM(E70:L70) -> 74390 | N70: =(E70+F70)*8% -> 2400 | O70: 5000 | P70: 0 | Q70: 0 | R70: 0 | S70: 0 | T70: 4480 | U70: 0 | V70: =SUM(N70:U70) -> 11880 | W70: =M70-V70 -> 62510 | X70: =(E70+F70)*12% -> 3600 | Y70: =(E70+F70)*3% -> 900 | AA70: =A70&B70 -> 46235T M R L B Thennakoon
A71: 46235 | B71: W K Senaverathna | C71: 24 | D71: Field Executive | E71: 31500 | F71: 3500 | G71: 7500 | H71: 5000 | I71: 26910 | J71: 0 | K71: 1000 | L71: 5260 | M71: =SUM(E71:L71) -> 80670 | N71: =(E71+F71)*8% -> 2800 | O71: 5000 | P71: 0 | Q71: 0 | R71: 0 | S71: 0 | T71: 5260 | U71: 0 | V71: =SUM(N71:U71) -> 13060 | W71: =M71-V71 -> 67610 | X71: =(E71+F71)*12% -> 4200 | Y71: =(E71+F71)*3% -> 1050 | AA71: =A71&B71 -> 46235W K Senaverathna
A72: 46235 | B72: D R G S L Ranaweera | C72: 25 | D72: Field Executive | E72: 36500 | F72: 3500 | G72: 5000 | H72: 5000 | I72: 26910 | J72: 10000 | K72: 1000 | L72: 5780 | M72: =SUM(E72:L72) -> 93690 | N72: =(E72+F72)*8% -> 3200 | O72: 16000 | P72: 0 | Q72: 10000 | R72: 900 | S72: 0 | T72: 5780 | U72: 0 | V72: =SUM(N72:U72) -> 35880 | W72: =M72-V72 -> 57810 | X72: =(E72+F72)*12% -> 4800 | Y72: =(E72+F72)*3% -> 1200 | Z72: 4/6 | AA72: =A72&B72 -> 46235D R G S L Ranaweera
A73: 46235 | B73: W A A Heshani Bandara | C73: 26 | D73: Trainee Account Clark | E73: 26500 | F73: 3500 | G73: 0 | H73: 0 | I73: 0 | J73: 0 | K73: 1000 | L73: 3000 | M73: =SUM(E73:L73) -> 34000 | N73: =(E73+F73)*8% -> 2400 | O73: 13000 | P73: 0 | Q73: 0 | R73: 0 | S73: 0 | T73: 3000 | U73: 0 | V73: =SUM(N73:U73) -> 18400 | W73: =M73-V73 -> 15600 | X73: =(E73+F73)*12% -> 3600 | Y73: =(E73+F73)*3% -> 900 | AA73: =A73&B73 -> 46235W A A Heshani Bandara
A74: 46235 | B74: D M T S Disanayake | C74: 27 | D74: Trainee Field Executive | E74: 26500 | F74: 3500 | G74: 2500 | H74: 2500 | I74: 24840 | J74: 10000 | K74: 1000 | L74: 5305 | M74: =SUM(E74:L74) -> 76145 | N74: =(E74+F74)*8% -> 2400 | O74: 5000 | P74: 0 | Q74: 10000 | R74: 2700 | S74: 0 | T74: 5305 | U74: 0 | V74: =SUM(N74:U74) -> 25405 | W74: =M74-V74 -> 50740 | X74: =(E74+F74)*12% -> 3600 | Y74: =(E74+F74)*3% -> 900 | Z74: 1/9 | AA74: =A74&B74 -> 46235D M T S Disanayake
A75: 46235 | B75: P L D B Wijewardhna | C75: 28 | D75: Field Executive | E75: 36500 | F75: 3500 | G75: 10000 | H75: 5000 | I75: 26910 | J75: 10000 | K75: 1000 | L75: 7745 | M75: =SUM(E75:L75) -> 100655 | N75: =(E75+F75)*8% -> 3200 | O75: 15000 | P75: 0 | Q75: 0 | R75: 0 | S75: 0 | T75: 7745 | U75: 0 | V75: =SUM(N75:U75) -> 25945 | W75: =M75-V75 -> 74710 | X75: =(E75+F75)*12% -> 4800 | Y75: =(E75+F75)*3% -> 1200 | AA75: =A75&B75 -> 46235P L D B Wijewardhna
A76: 46235 | B76: N G L D Supunsiri | C76: 29 | D76: Trainee Field Executive | E76: 26500 | F76: 3500 | G76: 5000 | H76: 5000 | I76: 18630 | J76: 0 | K76: 1000 | L76: 0 | M76: =SUM(E76:L76) -> 59630 | N76: =(E76+F76)*8% -> 2400 | O76: 11000 | P76: 0 | Q76: 0 | R76: 0 | S76: 0 | T76: 0 | U76: 0 | V76: =SUM(N76:U76) -> 13400 | W76: =M76-V76 -> 46230 | X76: =(E76+F76)*12% -> 3600 | Y76: =(E76+F76)*3% -> 900 | AA76: =A76&B76 -> 46235N G L D Supunsiri
A77: 46266 | B77: R A A S Ranasinghe | C77: 5 | D77: Director | E77: 61500 | F77: 3500 | G77: 53000 | H77: 0 | I77: 29000 | J77: 30000 | K77: 1000 | L77: 0 | M77: =SUM(E77:L77) -> 178000 | N77: =(E77+F77)*8% -> 5200 | O77: 102500 | P77: 0 | Q77: 9250 | R77: 2775 | S77: 0 | T77: 0 | U77: 1680 | V77: =SUM(N77:U77) -> 121405 | W77: =M77-V77 -> 56595 | X77: =(E77+F77)*12% -> 7800 | Y77: =(E77+F77)*3% -> 1950 | Z77: 6/20 | AA77: =A77&B77 -> 46266R A A S Ranasinghe
A78: 46266 | B78: P G U N Wimalasooriya | C78: 10 | D78: Account Assistant | E78: 26500 | F78: 3500 | G78: 5000 | H78: 0 | I78: 7000 | J78: 0 | K78: 1000 | L78: 1500 | M78: =SUM(E78:L78) -> 44500 | N78: =(E78+F78)*8% -> 2400 | O78: 2500 | P78: 0 | Q78: 7500 | R78: 450 | S78: 0 | T78: 1500 | U78: 0 | V78: =SUM(N78:U78) -> 14350 | W78: =M78-V78 -> 30150 | X78: =(E78+F78)*12% -> 3600 | Y78: =(E78+F78)*3% -> 900 | Z78: 1/2 | AA78: =A78&B78 -> 46266P G U N Wimalasooriya
A79: 46266 | B79: N M A G M Peiris | C79: 16 | D79: Assistant Branch Maneger | E79: 41500 | F79: 3500 | G79: 17000 | H79: 8000 | I79: 28980 | J79: 0 | K79: 1000 | L79: 3864 | M79: =SUM(E79:L79) -> 103844 | N79: =(E79+F79)*8% -> 3600 | O79: 17500 | P79: 0 | Q79: 12500 | R79: 3000 | S79: 0 | T79: 3864 | U79: 0 | V79: =SUM(N79:U79) -> 40464 | W79: =M79-V79 -> 63380 | X79: =(E79+F79)*12% -> 5400 | Y79: =(E79+F79)*3% -> 1350 | Z79: 1/8 | AA79: =A79&B79 -> 46266N M A G M Peiris
A80: 46266 | B80: K R T Hemantha | C80: 17 | D80: Field Executive | E80: 31500 | F80: 3500 | G80: 7500 | H80: 5000 | I80: 28980 | J80: 10000 | K80: 1000 | L80: 3260 | M80: =SUM(E80:L80) -> 90740 | N80: =(E80+F80)*8% -> 2800 | O80: 7500 | P80: 0 | Q80: 10000 | R80: 3000 | S80: 0 | T80: 3260 | U80: 0 | V80: =SUM(N80:U80) -> 26560 | W80: =M80-V80 -> 64180 | X80: =(E80+F80)*12% -> 4200 | Y80: =(E80+F80)*3% -> 1050 | Z80: 1/10 | AA80: =A80&B80 -> 46266K R T Hemantha
A81: 46266 | B81: W M H M Weerasinghe | C81: 18 | D81: Assistant Accountant | E81: 56500 | F81: 3500 | G81: 26000 | H81: 0 | I81: 13000 | J81: 0 | K81: 1000 | L81: 1500 | M81: =SUM(E81:L81) -> 101500 | N81: =(E81+F81)*8% -> 4800 | O81: 2500 | P81: 0 | Q81: 10000 | R81: 1200 | S81: 0 | T81: 1500 | U81: 0 | V81: =SUM(N81:U81) -> 20000 | W81: =M81-V81 -> 81500 | X81: =(E81+F81)*12% -> 7200 | Y81: =(E81+F81)*3% -> 1800 | Z81: 7/10 | AA81: =A81&B81 -> 46266W M H M Weerasinghe
A82: 46266 | B82: R W D S Wijerathna | C82: 19 | D82: Field Executive | E82: 36500 | F82: 3500 | G82: 7500 | H82: 5000 | I82: 28980 | J82: 10000 | K82: 1000 | L82: 8000 | M82: =SUM(E82:L82) -> 100480 | N82: =(E82+F82)*8% -> 3200 | O82: 2500 | P82: 0 | Q82: 8333.33 | R82: 249.9999 | T82: 8000 | U82: 0 | V82: =SUM(N82:U82) -> 22283.33 | W82: =M82-V82 -> 78196.67 | X82: =(E82+F82)*12% -> 4800 | Y82: =(E82+F82)*3% -> 1200 | Z82: 12/12 | AA82: =A82&B82 -> 46266R W D S Wijerathna
A83: 46266 | B83: S Wathmi Sankalpana | C83: 21 | D83: Trainee Account Clark | E83: 26500 | F83: 3500 | G83: 0 | H83: 0 | I83: 5000 | J83: 0 | K83: 1000 | L83: 1500 | M83: =SUM(E83:L83) -> 37500 | N83: =(E83+F83)*8% -> 2400 | O83: 4500 | P83: 0 | Q83: 6250 | R83: 750 | S83: 0 | T83: 1500 | U83: 0 | V83: =SUM(N83:U83) -> 15400 | W83: =M83-V83 -> 22100 | X83: =(E83+F83)*12% -> 3600 | Y83: =(E83+F83)*3% -> 900 | Z83: 1/4 | AA83: =A83&B83 -> 46266S Wathmi Sankalpana
A84: 46266 | B84: E M P P W O R K Jayawardana | C84: 22 | D84: Trainee Field Executive | E84: 26500 | F84: 3500 | G84: 5000 | H84: 2760 | I84: 26910 | J84: 10000 | K84: 1000 | L84: 6840 | M84: =SUM(E84:L84) -> 82510 | N84: =(E84+F84)*8% -> 2400 | O84: 2500 | P84: 0 | Q84: 5000 | R84: 1650 | S84: 0 | T84: 6840 | U84: 0 | V84: =SUM(N84:U84) -> 18390 | W84: =M84-V84 -> 64120 | X84: =(E84+F84)*12% -> 3600 | Y84: =(E84+F84)*3% -> 900 | Z84: 6/16 | AA84: =A84&B84 -> 46266E M P P W O R K Jayawardana
A85: 46266 | B85: T M R L B Thennakoon | C85: 23 | D85: Trainee Field Executive | E85: 26500 | F85: 3500 | G85: 7000 | H85: 5000 | I85: 28980 | J85: 0 | K85: 1000 | L85: 3840 | M85: =SUM(E85:L85) -> 75820 | N85: =(E85+F85)*8% -> 2400 | O85: 7500 | P85: 0 | Q85: 0 | R85: 0 | S85: 0 | T85: 3840 | U85: 0 | V85: =SUM(N85:U85) -> 13740 | W85: =M85-V85 -> 62080 | X85: =(E85+F85)*12% -> 3600 | Y85: =(E85+F85)*3% -> 900 | AA85: =A85&B85 -> 46266T M R L B Thennakoon
A86: 46266 | B86: W K Senaverathna | C86: 24 | D86: Field Executive | E86: 31500 | F86: 3500 | G86: 7500 | H86: 5000 | I86: 26910 | J86: 0 | K86: 1000 | L86: 6520 | M86: =SUM(E86:L86) -> 81930 | N86: =(E86+F86)*8% -> 2800 | O86: 2500 | P86: 0 | Q86: 0 | R86: 0 | S86: 0 | T86: 6520 | U86: 0 | V86: =SUM(N86:U86) -> 11820 | W86: =M86-V86 -> 70110 | X86: =(E86+F86)*12% -> 4200 | Y86: =(E86+F86)*3% -> 1050 | AA86: =A86&B86 -> 46266W K Senaverathna
A87: 46266 | B87: D R G S L Ranaweera | C87: 25 | D87: Field Executive | E87: 36500 | F87: 3500 | G87: 5000 | H87: 5000 | I87: 28980 | J87: 10000 | K87: 1000 | L87: 3220 | M87: =SUM(E87:L87) -> 93200 | N87: =(E87+F87)*8% -> 3200 | O87: 17500 | P87: 0 | Q87: 10000 | R87: 3000 | S87: 0 | T87: 3220 | U87: 0 | V87: =SUM(N87:U87) -> 36920 | W87: =M87-V87 -> 56280 | X87: =(E87+F87)*12% -> 4800 | Y87: =(E87+F87)*3% -> 1200 | Z87: 1/10 | AA87: =A87&B87 -> 46266D R G S L Ranaweera
A88: 46266 | B88: W A A Heshani Bandara | C88: 26 | D88: Trainee Account Clark | E88: 26500 | F88: 3500 | G88: 0 | H88: 0 | I88: 0 | J88: 0 | K88: 1000 | L88: 1500 | M88: =SUM(E88:L88) -> 32500 | N88: =(E88+F88)*8% -> 2400 | O88: 2500 | P88: 0 | Q88: 0 | R88: 0 | S88: 0 | T88: 1500 | U88: 0 | V88: =SUM(N88:U88) -> 6400 | W88: =M88-V88 -> 26100 | X88: =(E88+F88)*12% -> 3600 | Y88: =(E88+F88)*3% -> 900 | AA88: =A88&B88 -> 46266W A A Heshani Bandara
A89: 46266 | B89: D M T S Disanayake | C89: 27 | D89: Trainee Field Executive | E89: 26500 | F89: 3500 | G89: 2500 | H89: 2500 | I89: 24840 | J89: 10000 | K89: 1000 | L89: 8440 | M89: =SUM(E89:L89) -> 79280 | N89: =(E89+F89)*8% -> 2400 | O89: 2500 | P89: 0 | Q89: 10000 | R89: 2400 | S89: 0 | T89: 8440 | U89: 0 | V89: =SUM(N89:U89) -> 25740 | W89: =M89-V89 -> 53540 | X89: =(E89+F89)*12% -> 3600 | Y89: =(E89+F89)*3% -> 900 | Z89: 2/9 | AA89: =A89&B89 -> 46266D M T S Disanayake
A90: 46266 | B90: P L D B Wijewardhna | C90: 28 | D90: Field Executive | E90: 36500 | F90: 3500 | G90: 10000 | H90: 5000 | I90: 26910 | J90: 10000 | K90: 1000 | L90: 6720 | M90: =SUM(E90:L90) -> 99630 | N90: =(E90+F90)*8% -> 3200 | O90: 17500 | P90: 0 | Q90: 0 | R90: 0 | S90: 0 | T90: 6720 | U90: 0 | V90: =SUM(N90:U90) -> 27420 | W90: =M90-V90 -> 72210 | X90: =(E90+F90)*12% -> 4800 | Y90: =(E90+F90)*3% -> 1200 | AA90: =A90&B90 -> 46266P L D B Wijewardhna
A91: 46266 | B91: N G L D Supunsiri | C91: 29 | D91: Trainee Field Executive | E91: 26500 | F91: 3500 | G91: 5000 | H91: 5000 | I91: 18630 | J91: 0 | K91: 1000 | L91: 1500 | M91: =SUM(E91:L91) -> 61130 | N91: =(E91+F91)*8% -> 2400 | O91: 14500 | P91: 0 | Q91: 0 | R91: 0 | S91: 0 | T91: 1500 | U91: 0 | V91: =SUM(N91:U91) -> 18400 | W91: =M91-V91 -> 42730 | X91: =(E91+F91)*12% -> 3600 | Y91: =(E91+F91)*3% -> 900 | AA91: =A91&B91 -> 46266N G L D Supunsiri
A92: October 2026 | B92: R A A S Ranasinghe | C92: 5 | D92: Director | E92: 61500 | F92: 3500 | G92: 53000 | H92: 0 | I92: 29000 | J92: 30000 | K92: 1000 | L92: 0 | M92: =SUM(E92:L92) -> 178000 | N92: =(E92+F92)*8% -> 5200 | O92: 101850 | P92: 0 | Q92: 9250 | R92: 2590 | S92: 0 | T92: 0 | U92: 1680 | V92: =SUM(N92:U92) -> 120570 | W92: =M92-V92 -> 57430 | X92: =(E92+F92)*12% -> 7800 | Y92: =(E92+F92)*3% -> 1950 | AA92: =A92&B92 -> October 2026R A A S Ranasinghe
A93: October 2026 | B93: P G U N Wimalasooriya | C93: 10 | D93: Account Assistant | E93: 26500 | F93: 3500 | G93: 5000 | H93: 0 | I93: 7000 | J93: 0 | K93: 1000 | L93: 4382.5293 | M93: =SUM(E93:L93) -> 47382.529 | N93: =(E93+F93)*8% -> 2400 | O93: 5350 | P93: 0 | Q93: 7500 | R93: 225 | S93: 0 | T93: 4382.5293 | U93: 0 | V93: =SUM(N93:U93) -> 19857.529 | W93: =M93-V93 -> 27525 | X93: =(E93+F93)*12% -> 3600 | Y93: =(E93+F93)*3% -> 900 | AA93: =A93&B93 -> October 2026P G U N Wimalasooriya
A94: October 2026 | B94: N M A G M Peiris | C94: 16 | D94: Assistant Branch Maneger | E94: 41500 | F94: 3500 | G94: 17000 | H94: 8000 | I94: 28980 | J94: 0 | K94: 1000 | L94: 19899.09 | M94: =SUM(E94:L94) -> 119879.09 | N94: =(E94+F94)*8% -> 3600 | O94: 37850 | P94: 0 | Q94: 12500 | R94: 2625 | S94: 0 | T94: 19899.09 | U94: 0 | V94: =SUM(N94:U94) -> 76474.09 | W94: =M94-V94 -> 43405 | X94: =(E94+F94)*12% -> 5400 | Y94: =(E94+F94)*3% -> 1350 | AA94: =A94&B94 -> October 2026N M A G M Peiris
A95: October 2026 | B95: K R T Hemantha | C95: 17 | D95: Field Executive | E95: 31500 | F95: 3500 | G95: 7500 | H95: 5000 | I95: 28980 | J95: 10000 | K95: 1000 | L95: 15167.33 | M95: =SUM(E95:L95) -> 102647.33 | N95: =(E95+F95)*8% -> 2800 | O95: 12850 | P95: 0 | Q95: 10000 | R95: 2700 | S95: 0 | T95: 15167.33 | U95: 0 | V95: =SUM(N95:U95) -> 43517.33 | W95: =M95-V95 -> 59130 | X95: =(E95+F95)*12% -> 4200 | Y95: =(E95+F95)*3% -> 1050 | AA95: =A95&B95 -> October 2026K R T Hemantha
A96: October 2026 | B96: W M H M Weerasinghe | C96: 18 | D96: Assistant Accountant | E96: 56500 | F96: 3500 | G96: 26000 | H96: 0 | I96: 13000 | J96: 0 | K96: 1000 | L96: 4382.5293 | M96: =SUM(E96:L96) -> 104382.53 | N96: =(E96+F96)*8% -> 4800 | O96: 51850 | P96: 0 | Q96: 10000 | R96: 900 | S96: 0 | T96: 4382.5293 | U96: 0 | V96: =SUM(N96:U96) -> 71932.529 | W96: =M96-V96 -> 32450 | X96: =(E96+F96)*12% -> 7200 | Y96: =(E96+F96)*3% -> 1800 | AA96: =A96&B96 -> October 2026W M H M Weerasinghe
A97: October 2026 | B97: R W D S Wijerathna | C97: 19 | D97: Field Executive | E97: 36500 | F97: 3500 | G97: 7500 | H97: 5000 | I97: 28980 | J97: 10000 | K97: 1000 | L97: 11195.698 | M97: =SUM(E97:L97) -> 103675.7 | N97: =(E97+F97)*8% -> 3200 | O97: 1850 | P97: 0 | Q97: 0 | R97: 0 | S97: 0 | T97: 11195.698 | U97: 0 | V97: =SUM(N97:U97) -> 16245.698 | W97: =M97-V97 -> 87430 | X97: =(E97+F97)*12% -> 4800 | Y97: =(E97+F97)*3% -> 1200 | AA97: =A97&B97 -> October 2026R W D S Wijerathna
A98: October 2026 | B98: S Wathmi Sankalpana | C98: 21 | D98: Trainee Account Clark | E98: 26500 | F98: 3500 | G98: 0 | H98: 0 | I98: 5000 | J98: 0 | K98: 1000 | L98: 4382.5293 | M98: =SUM(E98:L98) -> 40382.529 | N98: =(E98+F98)*8% -> 2400 | O98: 3850 | P98: 0 | Q98: 6250 | R98: 562.5 | S98: 0 | T98: 4382.5293 | U98: 0 | V98: =SUM(N98:U98) -> 17445.029 | W98: =M98-V98 -> 22937.5 | X98: =(E98+F98)*12% -> 3600 | Y98: =(E98+F98)*3% -> 900 | AA98: =A98&B98 -> October 2026S Wathmi Sankalpana
A99: October 2026 | B99: E M P P W O R K Jayawardana | C99: 22 | D99: Trainee Field Executive | E99: 26500 | F99: 3500 | G99: 5000 | H99: 2760 | I99: 26910 | J99: 10000 | K99: 1000 | L99: 15081.56 | M99: =SUM(E99:L99) -> 90751.56 | N99: =(E99+F99)*8% -> 2400 | O99: 11850 | P99: 0 | Q99: 5000 | R99: 1500 | S99: 0 | T99: 15081.56 | U99: 0 | V99: =SUM(N99:U99) -> 35831.56 | W99: =M99-V99 -> 54920 | X99: =(E99+F99)*12% -> 3600 | Y99: =(E99+F99)*3% -> 900 | AA99: =A99&B99 -> October 2026E M P P W O R K Jayawardana
A100: October 2026 | B100: T M R L B Thennakoon | C100: 23 | D100: Trainee Field Executive | E100: 26500 | F100: 3500 | G100: 7000 | H100: 5000 | I100: 28980 | J100: 0 | K100: 1000 | L100: 17222.8 | M100: =SUM(E100:L100) -> 89202.8 | N100: =(E100+F100)*8% -> 2400 | O100: 7850 | P100: 0 | Q100: 0 | R100: 0 | S100: 0 | T100: 17222.8 | U100: 0 | V100: =SUM(N100:U100) -> 27472.8 | W100: =M100-V100 -> 61730 | X100: =(E100+F100)*12% -> 3600 | Y100: =(E100+F100)*3% -> 900 | AA100: =A100&B100 -> October 2026T M R L B Thennakoon
...
